vetting/__init__.py
vetting/centroiding.py
vetting/demo.png
vetting/version.py
vetting-0.3.1.dist-info/LICENSE
vetting-0.3.1.dist-info/WHEEL
vetting-0.3.1.dist-info/METADATA
vetting-0.3.1.dist-info/RECORD
