Metadata-Version: 2.1
Name: vetting
Version: 0.3.1
Summary: Simple, stand-alone vetting tools for transiting signals in Keper, K2 and TESS data
Home-page: https://github.com/SSDataLab/vetting
License: MIT
Keywords: NASA, Kepler, K2, TESS, Astronomy
Author: Christina Hedges
Author-email: christina.l.hedges@nasa.gov
Requires-Python: >=3.7,<4.0
Classifier: License :: OSI Approved :: MIT License
Classifier: Programming Language :: Python :: 3
Classifier: Programming Language :: Python :: 3.7
Classifier: Programming Language :: Python :: 3.8
Classifier: Programming Language :: Python :: 3.9
Classifier: Programming Language :: Python :: 3.10
Classifier: Programming Language :: Python :: 3.11
Requires-Dist: corner (>=2.1.0,<3.0.0)
Requires-Dist: lightkurve (>=2.0.9)
Project-URL: Repository, https://github.com/SSDataLab/vetting
